topasio/__init__.py
topasio/config.py
topasio/file_structure.py
topasio/logging_config.json
topasio/printing.py
topasio/py.typed
topasio/run.py
topasio/elements/geometry.py
topasio/elements/scorer.py
topasio/elements/source.py
topasio/generic_classes/element.py
topasio/generic_classes/space.py
topasio/generic_classes/tree.py
topasio/output_conversion/output_conversion.py
topasio/spaces/El.py
topasio/spaces/Ge.py
topasio/spaces/Gr.py
topasio/spaces/Is.py
topasio/spaces/Ma.py
topasio/spaces/Ph.py
topasio/spaces/Sc.py
topasio/spaces/So.py
topasio/spaces/Tf.py
topasio/spaces/Ts.py
topasio/spaces/Vr.py
topasio-1.0.3.dist-info/METADATA
topasio-1.0.3.dist-info/WHEEL
topasio-1.0.3.dist-info/RECORD
