Metadata-Version: 2.4
Name: topasio
Version: 1.0.3
Summary: Automation of (Open)TOPAS scripts, allowing for type inference and better access to parameters
Author-email: PinoLG01 <zuello.01@gmail.com>
Requires-Python: >=3.10
Requires-Dist: pandas>=2.3.0
Requires-Dist: polars>=1.31.0
Requires-Dist: pyarrow>=20.0.0
Requires-Dist: python-calamine>=0.3.2
Requires-Dist: quantities>=0.16.2
Requires-Dist: rich>=14.0.0
Requires-Dist: xlsxwriter>=3.2.5
